nudged/__init__.py
nudged/estimate.py
nudged/transform.py
nudged/version.py
nudged-0.3.1.dist-info/DESCRIPTION.rst
nudged-0.3.1.dist-info/METADATA
nudged-0.3.1.dist-info/RECORD
nudged-0.3.1.dist-info/WHEEL
nudged-0.3.1.dist-info/metadata.json
nudged-0.3.1.dist-info/top_level.txt
