Metadata-Version: 1.1
Name: nudged
Version: 0.3.1
Summary: Estimate scale, rotation, and translation between two sets of 2D points e.g. for multi-touch gestures or calibration
Home-page: https://github.com/axelpale/nudged-py
Author: Akseli Palen
Author-email: akseli.palen@gmail.com
License: MIT
Keywords: transformation calibration multitouch affine estimation
Platform: UNKNOWN
Classifier: Development Status :: 5 - Production/Stable
Classifier: Intended Audience :: Developers
Classifier: Intended Audience :: Science/Research
Classifier: Topic :: Scientific/Engineering :: Mathematics
Classifier: Topic :: Scientific/Engineering :: Image Recognition
Classifier: Topic :: Scientific/Engineering :: Human Machine Interfaces
Classifier: License :: OSI Approved :: MIT License
Classifier: Programming Language :: Python :: 2
Classifier: Programming Language :: Python :: 3
Classifier: Operating System :: OS Independent
